pytwot/__init__.py
pytwot/__main__.py
pytwot/attachments.py
pytwot/auth.py
pytwot/client.py
pytwot/compliance.py
pytwot/constants.py
pytwot/entities.py
pytwot/enums.py
pytwot/environment.py
pytwot/errors.py
pytwot/events.py
pytwot/http.py
pytwot/list.py
pytwot/message.py
pytwot/objects.py
pytwot/paginations.py
pytwot/parser.py
pytwot/py.typed
pytwot/relations.py
pytwot/space.py
pytwot/stream.py
pytwot/tweet.py
pytwot/type.py
pytwot/user.py
pytwot/utils.py
pytwot/dataclass/__init__.py
pytwot/dataclass/app.py
pytwot/dataclass/attachments.py
pytwot/dataclass/compliance.py
pytwot/dataclass/embed.py
pytwot/dataclass/locations.py
pytwot/dataclass/message.py
pytwot/dataclass/metrics.py
pytwot/dataclass/settings.py
pytwot/dataclass/space.py
pytwot/dataclass/stream.py
pytwot/threads/__init__.py
pytwot-1.5.1.dist-info/LICENSE
pytwot-1.5.1.dist-info/METADATA
pytwot-1.5.1.dist-info/WHEEL
pytwot-1.5.1.dist-info/top_level.txt
pytwot-1.5.1.dist-info/RECORD
