Metadata-Version: 2.1
Name: pytwot
Version: 1.5.1
Summary: A Synchronous python API wrapper for twitter's api
Home-page: https://github.com/sengolda/pytwot
Author: Sengolda
Maintainer: Sengolda
License: MIT
Project-URL: Documentation, https://py-tweet.readthedocs.io/
Project-URL: HomePage/Github, https://github.com/sengolda/pytwot/
Project-URL: Discord, https://discord.gg/XHBhg6A4jJ
Keywords: twitter,tweet.py twitter.py
Platform: UNKNOWN
Classifier: License :: OSI Approved :: MIT License
Classifier: Programming Language :: Python :: 3.7
Classifier: Programming Language :: Python :: 3.8
Classifier: Programming Language :: Python :: 3.9
Classifier: Programming Language :: Python :: 3.10
Classifier: Operating System :: OS Independent
Classifier: Topic :: Internet
Classifier: Topic :: Utilities
Classifier: Development Status :: 5 - Production/Stable
Requires-Python: >=3.7.0
License-File: LICENSE
Requires-Dist: Flask
Requires-Dist: python-dateutil
Requires-Dist: requests
Requires-Dist: requests-oauthlib
Provides-Extra: docs
Requires-Dist: furo (==2021.11.23) ; extra == 'docs'
Requires-Dist: sphinx (>=4.0.2) ; extra == 'docs'
Requires-Dist: sphinx-copybutton (>=0.4.0) ; extra == 'docs'
Provides-Extra: events
Requires-Dist: Flask (>=2.0.2) ; extra == 'events'
